promisipy/__init__.py
promisipy-0.1.3.dist-info/METADATA
promisipy-0.1.3.dist-info/WHEEL
promisipy-0.1.3.dist-info/licenses/LICENSE
promisipy-0.1.3.dist-info/RECORD
