Metadata-Version: 2.1
Name: promisipy
Version: 0.1.3
Summary: This Python library provides a flexible and easy-to-use asynchronous programming model based on the concept of promises, similar to those found in JavaScript.
Project-URL: Homepage, https://github.com/zpaceway/promisipy
Project-URL: Issues, https://github.com/zpaceway/promisipy/issues
Author-email: Alexandro Tapia <zpaceway@gmail.com>
License-File: LICENSE
Classifier: License :: OSI Approved :: MIT License
Classifier: Operating System :: OS Independent
Classifier: Programming Language :: Python :: 3
Requires-Python: >=3.8
